flatstar/__init__.py
flatstar/draw.py
flatstar/limb_darkening.py
flatstar/utils.py
flatstar-0.2.1a0.dist-info/LICENSE
flatstar-0.2.1a0.dist-info/METADATA
flatstar-0.2.1a0.dist-info/WHEEL
flatstar-0.2.1a0.dist-info/top_level.txt
flatstar-0.2.1a0.dist-info/RECORD
