Metadata-Version: 2.1
Name: flatstar
Version: 0.2.1a0
Summary: Draw limb-darkened stars!
Home-page: https://github.com/ladsantos/flatstar
Author: Leonardo dos Santos
Author-email: Leonardo.dosSantos@unige.ch
License: MIT
Platform: UNKNOWN
Classifier: Development Status :: 3 - Alpha
Classifier: Intended Audience :: Science/Research
Classifier: License :: OSI Approved :: MIT License
Classifier: Operating System :: OS Independent
Classifier: Programming Language :: Python
Requires-Dist: numpy
Requires-Dist: pillow
